README.md
setup.py
fontin/__init__.py
fontin/__main__.py
fontin/install_font.py
fontin.egg-info/PKG-INFO
fontin.egg-info/SOURCES.txt
fontin.egg-info/dependency_links.txt
fontin.egg-info/entry_points.txt
fontin.egg-info/requires.txt
fontin.egg-info/top_level.txt