Metadata-Version: 2.1
Name: fontin
Version: 0.0.10
Summary: A better font extractor and installer for bulk fonts in one archive.
Home-page: https://github.com/laxyapahuja/font-in
Author: Laxya Pahuja
Author-email: laxya.pahuja8@gmail.com
License: UNKNOWN
Project-URL: Documentation, https://github.com/laxyapahuja/font-in/README.md
Project-URL: Source, https://github.com/laxyapahuja/font-in
Platform: UNKNOWN
Classifier: Programming Language :: Python :: 3
Classifier: License :: OSI Approved :: MIT License
Classifier: Operating System :: OS Independent
Requires-Python: >=3.6
